creep/__init__.py
creep/creep.py
creep/src/__init__.py
creep/src/action.py
creep/src/application.py
creep/src/configuration.py
creep/src/factory.py
creep/src/logger.py
creep/src/path.py
creep/src/process.py
creep/src/revision.py
creep/src/source.py
creep/src/deployers/__init__.py
creep/src/deployers/console.py
creep/src/deployers/file.py
creep/src/deployers/ftp.py
creep/src/deployers/ssh.py
creep/src/trackers/__init__.py
creep/src/trackers/git.py
creep/src/trackers/hash.py
creep-0.5.2.dist-info/LICENSE.md
creep-0.5.2.dist-info/METADATA
creep-0.5.2.dist-info/WHEEL
creep-0.5.2.dist-info/entry_points.txt
creep-0.5.2.dist-info/top_level.txt
creep-0.5.2.dist-info/RECORD
