Metadata-Version: 2.1
Name: creep
Version: 0.5.2
Summary: Incremental FTP/SSH deployment tool
Home-page: https://github.com/r3c/creep
Author: Remi Caput
Author-email: v.python.org+creep@mirari.fr
License: MIT
Keywords: deploy deployment incremetal ftp ssh git
Platform: UNKNOWN
Classifier: Development Status :: 4 - Beta
Classifier: Environment :: Console
Classifier: Intended Audience :: Developers
Classifier: Intended Audience :: System Administrators
Classifier: License :: OSI Approved :: MIT License
Classifier: Programming Language :: Python :: 3.9
Classifier: Topic :: Software Development :: Build Tools
Classifier: Topic :: System :: Archiving :: Mirroring
Classifier: Topic :: System :: Software Distribution
License-File: LICENSE.md
Requires-Dist: setuptools (>=1.0)
